{
  "id": "",
  "name": "",
  "font_family": "iconfont",
  "css_prefix_text": "icon-",
  "description": "",
  "glyphs": [
    {
      "icon_id": "14732",
      "name": "向下",
      "font_class": "xiangxia",
      "unicode": "f02a9",
      "unicode_decimal": 983721
    },
    {
      "icon_id": "136387",
      "name": "下载",
      "font_class": "xiazai",
      "unicode": "f0304",
      "unicode_decimal": 983812
    },
    {
      "icon_id": "319471",
      "name": "play",
      "font_class": "play",
      "unicode": "e62e",
      "unicode_decimal": 58926
    },
    {
      "icon_id": "572242",
      "name": "hot",
      "font_class": "hot",
      "unicode": "e619",
      "unicode_decimal": 58905
    },
    {
      "icon_id": "5016733",
      "name": "橙子",
      "font_class": "chengzi",
      "unicode": "e607",
      "unicode_decimal": 58887
    },
    {
      "icon_id": "5772879",
      "name": "下一页",
      "font_class": "next",
      "unicode": "e61a",
      "unicode_decimal": 58906
    },
    {
      "icon_id": "8843484",
      "name": "折叠",
      "font_class": "zhedie",
      "unicode": "e643",
      "unicode_decimal": 58947
    },
    {
      "icon_id": "10678434",
      "name": "search",
      "font_class": "search",
      "unicode": "e6e1",
      "unicode_decimal": 59105
    },
    {
      "icon_id": "13636966",
      "name": "目录",
      "font_class": "mulu",
      "unicode": "e64e",
      "unicode_decimal": 58958
    },
    {
      "icon_id": "15617011",
      "name": "hot",
      "font_class": "hot1",
      "unicode": "e88c",
      "unicode_decimal": 59532
    }
  ]
}
